{"title": "Appartement 2 pi\u00e8ces, 33m\u00b2, Paris 14\u00e8me", "price": "\u20ac1\u00a0095", "body": "\n\nQR Code Link to This Post\n\n\nPERNETY / AL\u00c9SIA\n\nRUE DE LA SABLI\u00c8RE A 5-6 min des m\u00e9tros Pernety (Ligne 13) et Al\u00e9sia (Ligne 4), dans un immeuble des ann\u00e9es 30 avec gardien, deux pi\u00e8ces meubl\u00e9 de 33.32m\u00b2 traversant et refait \u00e0 neuf.\nIl est situ\u00e9 au RDC et se compose d'un s\u00e9jour avec cuisine US sur rue (plaques de cuisson, hotte, micro-ondes, r\u00e9frig\u00e9rateur avec bac cong\u00e9lation, lave-linge), d'une salle d'eau avec WC et d'une chambre avec grands placards sur cour. \nParquet, eau chaude et chauffage semi-collectif (compris dans les charges). Situ\u00e9 dans une rue calme \u00e0 2 min de la place Flora Tristan avec ses caf\u00e9s, dans un quartier authentiquement parisien avec de nombreux commerces.    ", "post_id": "7292618063", "created_time": "2021-03-17T11:52:30+0100", "images": [{"url": "https://images.craigslist.org/00X0X_1WMUpODiTNRz_0lM0t2_600x450.jpg", "flag": false}, {"url": "https://images.craigslist.org/00D0D_dAW9g8vkrc7z_0s90t2_600x450.jpg", "flag": false}, {"url": "https://images.craigslist.org/00t0t_fN5bZgAICxLz_0CI0t2_600x450.jpg", "flag": false}, {"url": "https://images.craigslist.org/00R0R_5vWjyqgohIUz_0lM0t2_600x450.jpg", "flag": false}, {"url": "https://images.craigslist.org/00W0W_4vln1GfJObz_0CI0t2_600x450.jpg", "flag": false}, {"url": "https://images.craigslist.org/00O0O_5Htg87B9jECz_0CI0t2_600x450.jpg", "flag": false}, {"url": "https://images.craigslist.org/00y0y_5LfF3flYJ9Vz_0CI0t2_600x450.jpg", "flag": false}]}